yea/__init__.py
yea/_setup.py
yea/_trigger.py
yea/cli.py
yea/config.py
yea/context.py
yea/plugins.py
yea/registry.py
yea/result.py
yea/runner.py
yea/schema-yea.json
yea/schema.py
yea/split.py
yea/testcfg.py
yea/testspec.py
yea/util.py
yea/yeadoc.py
yea/ytest.py
yea/vendor/junit_xml/wandb_junit_xml/__init__.py
yea-0.9.2.dist-info/LICENSE
yea-0.9.2.dist-info/METADATA
yea-0.9.2.dist-info/WHEEL
yea-0.9.2.dist-info/entry_points.txt
yea-0.9.2.dist-info/top_level.txt
yea-0.9.2.dist-info/RECORD
