Metadata-Version: 2.1
Name: yea
Version: 0.9.2
Summary: Test harness breaking the sound barrier
License: MIT license
Requires-Python: >=3.8
License-File: LICENSE
Requires-Dist: coverage
Requires-Dist: importlib-metadata >=3.0.0
Requires-Dist: jsonschema
Requires-Dist: PyYAML
Requires-Dist: requests
Requires-Dist: six
Requires-Dist: typing-extensions
Requires-Dist: uv
